[{
  "lng": -122.2603226,
  "locName": "Lake Merritt--outflow channel",
  "howMany": 4,
  "sciName": "Bucephala albeola",
  "obsValid": true,
  "locationPrivate": false,
  "obsDt": "2017-03-09 14:07",
  "obsReviewed": false,
  "comName": "Bufflehead",
  "lat": 37.7951354,
  "locID": "L803642"
}, {
  "lng": -122.2603226,
  "locName": "Lake Merritt--outflow channel",
  "howMany": 1,
  "sciName": "Fulica americana",
  "obsValid": true,
  "locationPrivate": false,
  "obsDt": "2017-03-09 14:07",
  "obsReviewed": false,
  "comName": "American Coot",
  "lat": 37.7951354,
  "locID": "L803642"
}, {
  "lng": -122.2603226,
  "locName": "Lake Merritt--outflow channel",
  "howMany": 2,
  "sciName": "Bucephala clangula",
  "obsValid": true,
  "locationPrivate": false,
  "obsDt": "2017-03-09 14:07",
  "obsReviewed": false,
  "comName": "Common Goldeneye",
  "lat": 37.7951354,
  "locID": "L803642"
}, {
  "lng": -122.2695289,
  "locName": "17th & Broadway, Oakland",
  "howMany": 6,
  "sciName": "Corvus brachyrhynchos",
  "obsValid": true,
  "locationPrivate": true,
  "obsDt": "2017-03-07 17:30",
  "obsReviewed": false,
  "comName": "American Crow",
  "lat": 37.8063719,
  "locID": "L1885363"
}, {
  "lng": -122.2695289,
  "locName": "17th & Broadway, Oakland",
  "howMany": 4,
  "sciName": "Larus occidentalis",
  "obsValid": true,
  "locationPrivate": true,
  "obsDt": "2017-03-07 17:30",
  "obsReviewed": false,
  "comName": "Western Gull",
  "lat": 37.8063719,
  "locID": "L1885363"
}, {
  "lng": -122.2695289,
  "locName": "17th & Broadway, Oakland",
  "howMany": 1,
  "sciName": "Columba livia",
  "obsValid": true,
  "locationPrivate": true,
  "obsDt": "2017-03-07 17:30",
  "obsReviewed": false,
  "comName": "Rock Pigeon",
  "lat": 37.8063719,
  "locID": "L1885363"
}, {
  "lng": -122.2695289,
  "locName": "17th & Broadway, Oakland",
  "howMany": 3,
  "sciName": "Larinae sp.",
  "obsValid": true,
  "locationPrivate": true,
  "obsDt": "2017-03-07 17:30",
  "obsReviewed": false,
  "comName": "gull sp.",
  "lat": 37.8063719,
  "locID": "L1885363"
}, {
  "lng": -122.2795594,
  "locName": "Ferry Dock",
  "howMany": 1,
  "sciName": "Nycticorax nycticorax",
  "obsValid": true,
  "locationPrivate": true,
  "obsDt": "2017-03-07 12:23",
  "obsReviewed": false,
  "comName": "Black-crowned Night-Heron",
  "lat": 37.7952032,
  "locID": "L4003930"
}, {
  "lng": -122.2795594,
  "locName": "Ferry Dock",
  "howMany": 1,
  "sciName": "Aechmophorus occidentalis/clarkii",
  "obsValid": true,
  "locationPrivate": true,
  "obsDt": "2017-03-07 12:23",
  "obsReviewed": false,
  "comName": "Western/Clark's Grebe",
  "lat": 37.7952032,
  "locID": "L4003930"
}, {
  "lng": -122.2795594,
  "locName": "Ferry Dock",
  "howMany": 1,
  "sciName": "Actitis macularius",
  "obsValid": true,
  "locationPrivate": true,
  "obsDt": "2017-03-07 12:23",
  "obsReviewed": false,
  "comName": "Spotted Sandpiper",
  "lat": 37.7952032,
  "locID": "L4003930"
}, {
  "lng": -122.2795594,
  "locName": "Ferry Dock",
  "howMany": 1,
  "sciName": "Egretta thula",
  "obsValid": true,
  "locationPrivate": true,
  "obsDt": "2017-03-07 12:23",
  "obsReviewed": false,
  "comName": "Snowy Egret",
  "lat": 37.7952032,
  "locID": "L4003930"
}, {
  "lng": -122.2795594,
  "locName": "Ferry Dock",
  "howMany": 3,
  "sciName": "Larus delawarensis",
  "obsValid": true,
  "locationPrivate": true,
  "obsDt": "2017-03-07 12:23",
  "obsReviewed": false,
  "comName": "Ring-billed Gull",
  "lat": 37.7952032,
  "locID": "L4003930"
}, {
  "lng": -122.2795594,
  "locName": "Ferry Dock",
  "howMany": 20,
  "sciName": "Larus canus",
  "obsValid": true,
  "locationPrivate": true,
  "obsDt": "2017-03-07 12:23",
  "obsReviewed": false,
  "comName": "Mew Gull",
  "lat": 37.7952032,
  "locID": "L4003930"
}, {
  "lng": -122.2795594,
  "locName": "Ferry Dock",
  "howMany": 5,
  "sciName": "Calidris minutilla",
  "obsValid": true,
  "locationPrivate": true,
  "obsDt": "2017-03-07 12:23",
  "obsReviewed": false,
  "comName": "Least Sandpiper",
  "lat": 37.7952032,
  "locID": "L4003930"
}, {
  "lng": -122.258563,
  "locName": "Gardens at Lake Merritt",
  "howMany": 2,
  "sciName": "Calypte anna",
  "obsValid": true,
  "locationPrivate": true,
  "obsDt": "2017-03-06 11:30",
  "obsReviewed": false,
  "comName": "Anna's Hummingbird",
  "lat": 37.8071116,
  "locID": "L2711945"
}, {
  "lng": -122.258563,
  "locName": "Gardens at Lake Merritt",
  "howMany": 1,
  "sciName": "Thryomanes bewickii",
  "obsValid": true,
  "locationPrivate": true,
  "obsDt": "2017-03-06 11:30",
  "obsReviewed": false,
  "comName": "Bewick's Wren",
  "lat": 37.8071116,
  "locID": "L2711945"
}, {
  "lng": -122.258563,
  "locName": "Gardens at Lake Merritt",
  "howMany": 2,
  "sciName": "Sayornis nigricans",
  "obsValid": true,
  "locationPrivate": true,
  "obsDt": "2017-03-06 11:30",
  "obsReviewed": false,
  "comName": "Black Phoebe",
  "lat": 37.8071116,
  "locID": "L2711945"
}, {
  "lng": -122.258563,
  "locName": "Gardens at Lake Merritt",
  "howMany": 1,
  "sciName": "Certhia americana",
  "obsValid": true,
  "locationPrivate": true,
  "obsDt": "2017-03-06 11:30",
  "obsReviewed": false,
  "comName": "Brown Creeper",
  "lat": 37.8071116,
  "locID": "L2711945"
}, {
  "lng": -122.258563,
  "locName": "Gardens at Lake Merritt",
  "howMany": 3,
  "sciName": "Psaltriparus minimus",
  "obsValid": true,
  "locationPrivate": true,
  "obsDt": "2017-03-06 11:30",
  "obsReviewed": false,
  "comName": "Bushtit",
  "lat": 37.8071116,
  "locID": "L2711945"
}, {
  "lng": -122.258563,
  "locName": "Gardens at Lake Merritt",
  "howMany": 2,
  "sciName": "Larus californicus",
  "obsValid": true,
  "locationPrivate": true,
  "obsDt": "2017-03-06 11:30",
  "obsReviewed": false,
  "comName": "California Gull",
  "lat": 37.8071116,
  "locID": "L2711945"
}, {
  "lng": -122.258563,
  "locName": "Gardens at Lake Merritt",
  "howMany": 3,
  "sciName": "Melozone crissalis",
  "obsValid": true,
  "locationPrivate": true,
  "obsDt": "2017-03-06 11:30",
  "obsReviewed": false,
  "comName": "California Towhee",
  "lat": 37.8071116,
  "locID": "L2711945"
}, {
  "lng": -122.258563,
  "locName": "Gardens at Lake Merritt",
  "howMany": 6,
  "sciName": "Branta canadensis",
  "obsValid": true,
  "locationPrivate": true,
  "obsDt": "2017-03-06 11:30",
  "obsReviewed": false,
  "comName": "Canada Goose",
  "lat": 37.8071116,
  "locID": "L2711945"
}, {
  "lng": -122.258563,
  "locName": "Gardens at Lake Merritt",
  "howMany": 2,
  "sciName": "Junco hyemalis",
  "obsValid": true,
  "locationPrivate": true,
  "obsDt": "2017-03-06 11:30",
  "obsReviewed": false,
  "comName": "Dark-eyed Junco",
  "lat": 37.8071116,
  "locID": "L2711945"
}, {
  "lng": -122.258563,
  "locName": "Gardens at Lake Merritt",
  "howMany": 1,
  "sciName": "Picoides pubescens",
  "obsValid": true,
  "locationPrivate": true,
  "obsDt": "2017-03-06 11:30",
  "obsReviewed": false,
  "comName": "Downy Woodpecker",
  "lat": 37.8071116,
  "locID": "L2711945"
}, {
  "lng": -122.258563,
  "locName": "Gardens at Lake Merritt",
  "howMany": 1,
  "sciName": "Podiceps nigricollis",
  "obsValid": true,
  "locationPrivate": true,
  "obsDt": "2017-03-06 11:30",
  "obsReviewed": false,
  "comName": "Eared Grebe",
  "lat": 37.8071116,
  "locID": "L2711945"
}, {
  "lng": -122.258563,
  "locName": "Gardens at Lake Merritt",
  "howMany": 1,
  "sciName": "Zonotrichia atricapilla",
  "obsValid": true,
  "locationPrivate": true,
  "obsDt": "2017-03-06 11:30",
  "obsReviewed": false,
  "comName": "Golden-crowned Sparrow",
  "lat": 37.8071116,
  "locID": "L2711945"
}, {
  "lng": -122.258563,
  "locName": "Gardens at Lake Merritt",
  "howMany": 1,
  "sciName": "Haemorhous mexicanus",
  "obsValid": true,
  "locationPrivate": true,
  "obsDt": "2017-03-06 11:30",
  "obsReviewed": false,
  "comName": "House Finch",
  "lat": 37.8071116,
  "locID": "L2711945"
}, {
  "lng": -122.258563,
  "locName": "Gardens at Lake Merritt",
  "howMany": 2,
  "sciName": "Anas platyrhynchos",
  "obsValid": true,
  "locationPrivate": true,
  "obsDt": "2017-03-06 11:30",
  "obsReviewed": false,
  "comName": "Mallard",
  "lat": 37.8071116,
  "locID": "L2711945"
}, {
  "lng": -122.258563,
  "locName": "Gardens at Lake Merritt",
  "howMany": 1,
  "sciName": "Picoides nuttallii",
  "obsValid": true,
  "locationPrivate": true,
  "obsDt": "2017-03-06 11:30",
  "obsReviewed": false,
  "comName": "Nuttall's Woodpecker",
  "lat": 37.8071116,
  "locID": "L2711945"
}, {
  "lng": -122.258563,
  "locName": "Gardens at Lake Merritt",
  "howMany": 4,
  "sciName": "Baeolophus inornatus",
  "obsValid": true,
  "locationPrivate": true,
  "obsDt": "2017-03-06 11:30",
  "obsReviewed": false,
  "comName": "Oak Titmouse",
  "lat": 37.8071116,
  "locID": "L2711945"
}, {
  "lng": -122.258563,
  "locName": "Gardens at Lake Merritt",
  "howMany": 1,
  "sciName": "Cyanocitta stelleri",
  "obsValid": true,
  "locationPrivate": true,
  "obsDt": "2017-03-06 11:30",
  "obsReviewed": false,
  "comName": "Steller's Jay",
  "lat": 37.8071116,
  "locID": "L2711945"
}, {
  "lng": -122.258563,
  "locName": "Gardens at Lake Merritt",
  "howMany": 2,
  "sciName": "Sialia mexicana",
  "obsValid": true,
  "locationPrivate": true,
  "obsDt": "2017-03-06 11:30",
  "obsReviewed": false,
  "comName": "Western Bluebird",
  "lat": 37.8071116,
  "locID": "L2711945"
}, {
  "lng": -122.258563,
  "locName": "Gardens at Lake Merritt",
  "howMany": 6,
  "sciName": "Zonotrichia leucophrys",
  "obsValid": true,
  "locationPrivate": true,
  "obsDt": "2017-03-06 11:30",
  "obsReviewed": false,
  "comName": "White-crowned Sparrow",
  "lat": 37.8071116,
  "locID": "L2711945"
}, {
  "lng": -122.258563,
  "locName": "Gardens at Lake Merritt",
  "howMany": 4,
  "sciName": "Setophaga coronata",
  "obsValid": true,
  "locationPrivate": true,
  "obsDt": "2017-03-06 11:30",
  "obsReviewed": false,
  "comName": "Yellow-rumped Warbler",
  "lat": 37.8071116,
  "locID": "L2711945"
}]
